{"StatID":2158012,"TeamID":9,"PlayerID":10000931,"SeasonType":1,"Season":2018,"Name":"Cole Hamels","Team":"CHC","Position":"SP","PositionCategory":"P","Started":32,"BattingOrder":null,"GlobalTeamID":10000009,"AverageDraftPosition":null,"Updated":"2018-12-31T03:19:03","Games":33,"FantasyPoints":175.4,"AtBats":28.2,"Runs":1.1,"Hits":3.4,"Singles":2.3,"Doubles":0,"Triples":0,"HomeRuns":1.1,"RunsBattedIn":1.1,"BattingAverage":0.1,"Outs":24.8,"Strikeouts":13.5,"Walks":1.1,"HitByPitch":0,"Sacrifices":1.1,"SacrificeFlies":0,"GroundIntoDoublePlay":0,"StolenBases":0,"CaughtStealing":0,"PitchesSeen":111.6,"OnBasePercentage":0.2,"SluggingPercentage":0.3,"OnBasePlusSlugging":0.4,"Errors":1.1,"Wins":10.1,"Losses":13.5,"Saves":0,"InningsPitchedDecimal":214.9,"TotalOutsPitched":644.6,"InningsPitchedFull":214.1,"InningsPitchedOuts":2.3,"EarnedRunAverage":4.3,"PitchingHits":198.4,"PitchingRuns":104.8,"PitchingEarnedRuns":90.2,"PitchingWalks":73.3,"PitchingStrikeouts":211.9,"PitchingHomeRuns":32.7,"PitchesThrown":3449.7,"PitchesThrownStrikes":2196.5,"WalksHitsPerInningsPitched":1.4,"PitchingBattingAverageAgainst":0.3,"GrandSlams":0,"FantasyPointsFanDuel":1142.8,"FantasyPointsDraftKings":594.5,"FantasyPointsYahoo":664.9,"PlateAppearances":29.3,"TotalBases":6.8,"FlyOuts":0,"GroundOuts":5.6,"LineOuts":1.1,"PopOuts":2.3,"IntentionalWalks":0,"ReachedOnError":0,"BallsInPlay":13.5,"BattingAverageOnBallsInPlay":0.2,"WeightedOnBasePercentage":0.2,"PitchingSingles":127.4,"PitchingDoubles":32.7,"PitchingTriples":5.6,"PitchingGrandSlams":1.1,"PitchingHitByPitch":21.4,"PitchingSacrifices":1.1,"PitchingSacrificeFlies":4.5,"PitchingGroundIntoDoublePlay":30.4,"PitchingCompleteGames":1.1,"PitchingShutOuts":0,"PitchingNoHitters":0,"PitchingPerfectGames":0,"PitchingPlateAppearances":908.4,"PitchingTotalBases":340.4,"PitchingFlyOuts":93.5,"PitchingGroundOuts":146.5,"PitchingLineOuts":57.5,"PitchingPopOuts":21.4,"PitchingIntentionalWalks":0,"PitchingReachedOnError":12.4,"PitchingCatchersInterference":2.3,"PitchingBallsInPlay":565.8,"PitchingOnBasePercentage":0.4,"PitchingSluggingPercentage":0.5,"PitchingOnBasePlusSlugging":0.8,"PitchingStrikeoutsPerNineInnings":10,"PitchingWalksPerNineInnings":3.5,"PitchingBattingAverageOnBallsInPlay":0.3,"PitchingWeightedOnBasePercentage":0.4,"DoublePlays":0,"PitchingDoublePlays":32.7,"BattingOrderConfirmed":true,"IsolatedPower":0.1,"FieldingIndependentPitching":5.1,"PitchingQualityStarts":18,"PitchingInningStarted":null,"LeftOnBase":16.9,"PitchingHolds":0,"PitchingBlownSaves":0,"SubstituteBattingOrder":null,"SubstituteBattingOrderSequence":null,"FantasyPointsFantasyDraft":594.5}