{"StatID":2253999,"TeamID":9,"PlayerID":10001891,"SeasonType":1,"Season":2018,"Name":"Justin Hancock","Team":"CHC","Position":"RP","PositionCategory":"P","Started":0,"BattingOrder":null,"GlobalTeamID":10000009,"AverageDraftPosition":null,"Updated":"2018-12-31T03:19:03","Games":10,"FantasyPoints":11.6,"AtBats":2.3,"Runs":0,"Hits":0,"Singles":0,"Doubles":0,"Triples":0,"HomeRuns":0,"RunsBattedIn":0,"BattingAverage":0,"Outs":2.3,"Strikeouts":2.3,"Walks":0,"HitByPitch":0,"Sacrifices":0,"SacrificeFlies":0,"GroundIntoDoublePlay":0,"StolenBases":0,"CaughtStealing":0,"PitchesSeen":11.3,"OnBasePercentage":0,"SluggingPercentage":0,"OnBasePlusSlugging":0,"Errors":0,"Wins":0,"Losses":0,"Saves":0,"InningsPitchedDecimal":13.9,"TotalOutsPitched":41.7,"InningsPitchedFull":13.5,"InningsPitchedOuts":1.1,"EarnedRunAverage":1.6,"PitchingHits":5.6,"PitchingRuns":2.3,"PitchingEarnedRuns":2.3,"PitchingWalks":10.1,"PitchingStrikeouts":12.4,"PitchingHomeRuns":1.1,"PitchesThrown":232.2,"PitchesThrownStrikes":139.7,"WalksHitsPerInningsPitched":1.3,"PitchingBattingAverageAgainst":0.1,"GrandSlams":0,"FantasyPointsFanDuel":72.1,"FantasyPointsDraftKings":42.1,"FantasyPointsYahoo":47.8,"PlateAppearances":2.3,"TotalBases":0,"FlyOuts":0,"GroundOuts":0,"LineOuts":0,"PopOuts":0,"IntentionalWalks":0,"ReachedOnError":0,"BallsInPlay":0,"BattingAverageOnBallsInPlay":0,"WeightedOnBasePercentage":0,"PitchingSingles":3.4,"PitchingDoubles":1.1,"PitchingTriples":0,"PitchingGrandSlams":0,"PitchingHitByPitch":0,"PitchingSacrifices":0,"PitchingSacrificeFlies":0,"PitchingGroundIntoDoublePlay":1.1,"PitchingCompleteGames":0,"PitchingShutOuts":0,"PitchingNoHitters":0,"PitchingPerfectGames":0,"PitchingPlateAppearances":55.2,"PitchingTotalBases":10.1,"PitchingFlyOuts":10.1,"PitchingGroundOuts":10.1,"PitchingLineOuts":4.5,"PitchingPopOuts":0,"PitchingIntentionalWalks":0,"PitchingReachedOnError":0,"PitchingCatchersInterference":0,"PitchingBallsInPlay":31.6,"PitchingOnBasePercentage":0.3,"PitchingSluggingPercentage":0.3,"PitchingOnBasePlusSlugging":0.6,"PitchingStrikeoutsPerNineInnings":9,"PitchingWalksPerNineInnings":7.4,"PitchingBattingAverageOnBallsInPlay":0.2,"PitchingWeightedOnBasePercentage":0.3,"DoublePlays":0,"PitchingDoublePlays":1.1,"BattingOrderConfirmed":true,"IsolatedPower":0,"FieldingIndependentPitching":5.2,"PitchingQualityStarts":0,"PitchingInningStarted":null,"LeftOnBase":3.4,"PitchingHolds":0,"PitchingBlownSaves":0,"SubstituteBattingOrder":null,"SubstituteBattingOrderSequence":null,"FantasyPointsFantasyDraft":42.1}