{"PlayerID":10008368,"SportsDataID":"","Status":"Minors","TeamID":9,"Team":"CHC","Jersey":34,"PositionCategory":"P","Position":"SP","MLBAMID":null,"FirstName":"Brendon","LastName":"Little","BatHand":"L","ThrowHand":"L","Height":null,"Weight":195,"BirthDate":null,"BirthCity":"Bryn Mawr","BirthState":"PA","BirthCountry":"USA","HighSchool":null,"College":null,"ProDebut":null,"Salary":null,"PhotoUrl":"https://s3-us-west-2.amazonaws.com/static.fantasydata.com/headshots/mlb/low-res/0.png","SportRadarPlayerID":"","RotoworldPlayerID":null,"RotoWirePlayerID":14796,"FantasyAlarmPlayerID":null,"StatsPlayerID":876266,"SportsDirectPlayerID":null,"XmlTeamPlayerID":null,"InjuryStatus":"Scrambled","InjuryBodyPart":"Scrambled","InjuryStartDate":null,"InjuryNotes":"Scrambled","FanDuelPlayerID":82549,"DraftKingsPlayerID":876266,"YahooPlayerID":null,"UpcomingGameID":53714,"FanDuelName":"Brendon Little","DraftKingsName":"Brendon Little","YahooName":null,"GlobalTeamID":10000009,"FantasyDraftName":"Brendon Little","FantasyDraftPlayerID":1266702,"Experience":null,"UsaTodayPlayerID":null,"UsaTodayHeadshotUrl":null,"UsaTodayHeadshotNoBackgroundUrl":null,"UsaTodayHeadshotUpdated":null,"UsaTodayHeadshotNoBackgroundUpdated":null}